levutils/__init__.py
levutils/mybag.py
levutils/myutils.py
levutils/util_jupyter.py
levutils-0.2.dist-info/LICENSE
levutils-0.2.dist-info/METADATA
levutils-0.2.dist-info/WHEEL
levutils-0.2.dist-info/top_level.txt
levutils-0.2.dist-info/RECORD
