Metadata-Version: 2.1
Name: levutils
Version: 0.2
Summary: A package containing modules mybag and myutils 
Home-page: https://github.com/yourusername/eais
Author: Lev Selector
Author-email: lev.selector@gmail.com
Classifier: Programming Language :: Python :: 3
Classifier: License :: OSI Approved :: MIT License
Classifier: Operating System :: OS Independent
License-File: LICENSE
Requires-Dist: pandas
Requires-Dist: numpy
Requires-Dist: unidecode
Requires-Dist: ipython
